novus_pytils/__init__.py
novus_pytils/exceptions.py
novus_pytils/globals.py
novus_pytils/audio/__init__.py
novus_pytils/audio/aac.py
novus_pytils/audio/core.py
novus_pytils/audio/flac.py
novus_pytils/audio/m4a.py
novus_pytils/audio/mp3.py
novus_pytils/audio/ogg.py
novus_pytils/audio/wav_parser.py
novus_pytils/audio/wave.py
novus_pytils/audio/wma.py
novus_pytils/audio/wrappers.py
novus_pytils/compression/__init__.py
novus_pytils/compression/core.py
novus_pytils/compression/zip.py
novus_pytils/files/__init__.py
novus_pytils/files/core.py
novus_pytils/image/__init__.py
novus_pytils/image/bmp.py
novus_pytils/image/core.py
novus_pytils/image/gif.py
novus_pytils/image/jpg.py
novus_pytils/image/png.py
novus_pytils/image/svg.py
novus_pytils/image/tiff.py
novus_pytils/image/webp.py
novus_pytils/image/wrappers.py
novus_pytils/text/__init__.py
novus_pytils/text/conf.py
novus_pytils/text/core.py
novus_pytils/text/csv.py
novus_pytils/text/ini.py
novus_pytils/text/json.py
novus_pytils/text/log.py
novus_pytils/text/md.py
novus_pytils/text/text.py
novus_pytils/text/txt.py
novus_pytils/text/xml.py
novus_pytils/text/yaml.py
novus_pytils/types/__init__.py
novus_pytils/types/lists.py
novus_pytils/types/pandas.py
novus_pytils/utils/__init__.py
novus_pytils/utils/console.py
novus_pytils/utils/hash.py
novus_pytils/utils/validation.py
novus_pytils/video/__init__.py
novus_pytils/video/avi.py
novus_pytils/video/core.py
novus_pytils/video/flv.py
novus_pytils/video/m4v.py
novus_pytils/video/mk4.py
novus_pytils/video/mov.py
novus_pytils/video/mp4.py
novus_pytils/video/video.py
novus_pytils/video/webm.py
novus_pytils/video/wmv.py
novus_pytils-0.0.64.dist-info/METADATA
novus_pytils-0.0.64.dist-info/WHEEL
novus_pytils-0.0.64.dist-info/RECORD
